ml_crafter/__init__.py
ml_crafter/data_preprocessing/__init__.py
ml_crafter/data_preprocessing/_data_types.py
ml_crafter/model_monitoring/__init__.py
ml_crafter/model_monitoring/_population_drift.py
ml_crafter/utils/__init__.py
ml_crafter/utils/compare_dataframes.py
ml_crafter/utils/compare_dataframes.py.py
ml_crafter-0.1.1.dist-info/LICENSE
ml_crafter-0.1.1.dist-info/METADATA
ml_crafter-0.1.1.dist-info/WHEEL
ml_crafter-0.1.1.dist-info/top_level.txt
ml_crafter-0.1.1.dist-info/RECORD
