Metadata-Version: 2.1
Name: ml-crafter
Version: 0.1.1
Summary: Performs end to end ML model development
License-File: LICENSE
Requires-Dist: numpy
Requires-Dist: scipy
